LICENSE
README.md
setup.cfg
setup.py
py_viper.egg-info/PKG-INFO
py_viper.egg-info/SOURCES.txt
py_viper.egg-info/dependency_links.txt
py_viper.egg-info/requires.txt
py_viper.egg-info/top_level.txt
viper/__init__.py
viper/flag.py
viper/remote.py
viper/viper.py