Metadata-Version: 2.1
Name: py-viper
Version: 0.1.0.dev5
Summary: Python viper
Home-page: https://github.com/shaneing/python-viper
Author: shaneing
Author-email: z.shane.ing@gamil.com
License: UNKNOWN
Platform: UNKNOWN
Classifier: Programming Language :: Python
Classifier: Operating System :: Microsoft :: Windows
Classifier: Operating System :: Unix
Classifier: Operating System :: MacOS
Classifier: Programming Language :: Python :: 3.4
Classifier: Programming Language :: Python :: 3.5
Classifier: Programming Language :: Python :: 3.6
Classifier: Programming Language :: Python :: 3.7
